autolabel4seg/__init__.py
autolabel4seg/create.py
autolabel4seg/labels.py
autolabel4seg/modules.py
autolabel4seg/modules_autolabel.py
autolabel4seg/modules_autolabel_class.py
autolabel4seg/modules_dataset.py
autolabel4seg/modules_doc.py
autolabel4seg/modules_plot.py
autolabel4seg/modules_predict.py
autolabel4seg/modules_video.py
autolabel4seg/modules_yolov8.py
autolabel4seg/plot.py
autolabel4seg/test.py
autolabel4seg/upload.py
autolabel4seg/upload_video.py
autolabel4seg-0.0.4.dist-info/LICENSE.txt
autolabel4seg-0.0.4.dist-info/METADATA
autolabel4seg-0.0.4.dist-info/WHEEL
autolabel4seg-0.0.4.dist-info/top_level.txt
autolabel4seg-0.0.4.dist-info/RECORD
