Metadata-Version: 2.1
Name: autolabel4seg
Version: 0.0.4
Summary: Create Object Segmentation Labels
Home-page: https://github.com/falahgs/
Author: Falahgs.G.Saleih
Author-email: falahgs07@gmail.com
License: MIT
Keywords: transformers,datasets
Classifier: Programming Language :: Python :: 3
Classifier: License :: OSI Approved :: MIT License
Classifier: Operating System :: OS Independent
Requires-Python: >=3.6
License-File: LICENSE.txt
Requires-Dist: reportlab
Requires-Dist: ultralytics
Requires-Dist: Pillow
Requires-Dist: roboflow
Requires-Dist: autodistill-grounded-sam ==0.1.1
Requires-Dist: google-images-downloader ==1.0.16
Requires-Dist: pytube
